{
  "unversionedId": "authentication/introduction",
  "id": "authentication/introduction",
  "isDocsHomePage": false,
  "title": "Introduction",
  "description": "If you don't have a registration and login method on your site or you want to use Logora's login module, go to your Administration Space tab Configuration > Authentication and choose the Social authentication mode. You can then go directly to the customization of your debate space.",
  "source": "@site/i18n\\en\\docusaurus-plugin-content-docs\\current\\authentication\\introduction.md",
  "slug": "/authentication/introduction",
  "permalink": "/en/authentication/introduction",
  "version": "current",
  "sidebar": "docs",
  "previous": {
    "title": "App SDK",
    "permalink": "/en/installation/app-sdk"
  },
  "next": {
    "title": "OAuth 2.0 server",
    "permalink": "/en/authentication/oauth2_server"
  }
}